{"Earth Spirit": "59.93", "Io": "57.00", "Morphling": "56.32", "Techies": "55.37", "Shadow Demon": "55.18", "Broodmother": "55.13", "Enchantress": "54.58", "Ember Spirit": "54.47", "Alchemist": "54.45", "Meepo": "54.33", "Puck": "54.02", "Legion Commander": "53.80", "Lone Druid": "53.38", "Anti-Mage": "53.35", "Chen": "53.29", "Timbersaw": "53.22", "Magnus": "53.08", "Outworld Devourer": "53.05", "Batrider": "52.97", "Tinker": "52.94", "Windranger": "52.89", "Queen of Pain": "52.89", "Storm Spirit": "52.86", "Rubick": "52.72", "Tusk": "52.67", "Gyrocopter": "52.51", "Phantom Assassin": "52.43", "Naga Siren": "52.41", "Invoker": "52.20", "Tiny": "52.01", "Templar Assassin": "52.00", "Bane": "51.88", "Lina": "51.73", "Pugna": "51.71", "Clinkz": "51.63", "Dragon Knight": "51.44", "Skywrath Mage": "51.44", "Axe": "51.15", "Bristleback": "50.87", "Chaos Knight": "50.57", "Leshrac": "50.53", "Enigma": "50.51", "Visage": "50.45", "Lion": "50.37", "Medusa": "50.35", "Beastmaster": "50.09", "Huskar": "50.04", "Doom": "49.90", "Dark Seer": "49.86", "Kunkka": "49.82", "Bounty Hunter": "49.82", "Troll Warlord": "49.77", "Undying": "49.67", "Lifestealer": "49.53", "Phoenix": "49.49", "Nature's Prophet": "49.30", "Dazzle": "49.26", "Terrorblade": "49.24", "Pudge": "49.11", "Shadow Fiend": "49.03", "Clockwerk": "48.98", "Sniper": "48.83", "Sand King": "48.57", "Disruptor": "48.45", "Faceless Void": "48.18", "Earthshaker": "48.17", "Shadow Shaman": "47.97", "Nyx Assassin": "47.96", "Slardar": "47.92", "Elder Titan": "47.83", "Keeper of the Light": "47.62", "Slark": "47.53", "Night Stalker": "47.31", "Weaver": "47.12", "Juggernaut": "46.99", "Ogre Magi": "46.91", "Sven": "46.90", "Razor": "46.89", "Witch Doctor": "46.74", "Crystal Maiden": "46.37", "Jakiro": "46.20", "Treant Protector": "46.20", "Bloodseeker": "46.12", "Venomancer": "46.07", "Mirana": "45.91", "Tidehunter": "45.68", "Omniknight": "45.67", "Silencer": "45.49", "Phantom Lancer": "45.15", "Spectre": "45.10", "Vengeful Spirit": "45.09", "Luna": "45.08", "Necrophos": "45.05", "Brewmaster": "45.04", "Riki": "44.67", "Viper": "44.52", "Death Prophet": "44.20", "Centaur Warrunner": "44.10", "Drow Ranger": "43.72", "Spirit Breaker": "43.56", "Wraith King": "43.34", "Abaddon": "43.32", "Ursa": "43.18", "Lich": "42.97", "Lycan": "42.96", "Warlock": "42.89", "Zeus": "41.24"}